custom_field_list.json
horusbinaryv3/HorusBinaryV3.asn1
horusdemodlib/__init__.py
horusdemodlib/checksums.py
horusdemodlib/decoder.py
horusdemodlib/delegates.py
horusdemodlib/demod.py
horusdemodlib/demodstats.py
horusdemodlib/encoder.py
horusdemodlib/horus_api_build.py
horusdemodlib/horusudp.py
horusdemodlib/payloads.py
horusdemodlib/sondehubamateur.py
horusdemodlib/uploader.py
horusdemodlib/utils.py
payload_id_list.txt
_horus_api_cffi.cp312-win_amd64.pyd
horusdemodlib-0.6.1.dist-info/entry_points.txt
horusdemodlib-0.6.1.dist-info/licenses/LICENSE
horusdemodlib-0.6.1.dist-info/METADATA
horusdemodlib-0.6.1.dist-info/WHEEL
horusdemodlib-0.6.1.dist-info/RECORD
