Metadata-Version: 2.4
Name: horusdemodlib
Version: 0.6.1
Summary: Project Horus HAB Telemetry Demodulators
License: LGPL-2.1-or-later
License-File: LICENSE
Author: Mark Jessop
Requires-Python: >=3.9,<4.0
Classifier: License :: OSI Approved
Classifier: Programming Language :: Python :: 3
Classifier: Programming Language :: Python :: 3.9
Classifier: Programming Language :: Python :: 3.10
Classifier: Programming Language :: Python :: 3.11
Classifier: Programming Language :: Python :: 3.12
Classifier: Programming Language :: Python :: 3.13
Classifier: Programming Language :: Python :: 3.14
Requires-Dist: asn1tools (>=0.165.0,<0.166.0)
Requires-Dist: audioop-lts ; python_version >= "3.13" and python_version < "4.0"
Requires-Dist: cffi (>1.14.0)
Requires-Dist: python-dateutil (>=2.8,<3.0)
Requires-Dist: requests (>=2.25.1,<3.0.0)
